{
    "frame1": {
        "Landmark1": [
            [
                151,
                913,
                6.022789307280618e-07
            ]
        ],
        "Landmark2": [
            [
                212,
                871,
                -0.03460906073451042
            ]
        ],
        "Landmark3": [
            [
                240,
                798,
                -0.04666948691010475
            ]
        ],
        "Landmark4": [
            [
                203,
                747,
                -0.06064802408218384
            ]
        ],
        "Landmark5": [
            [
                154,
                725,
                -0.07288859039545059
            ]
        ],
        "Landmark6": [
            [
                210,
                715,
                -0.01251962035894394
            ]
        ],
        "Landmark7": [
            [
                216,
                641,
                -0.03617006540298462
            ]
        ],
        "Landmark8": [
            [
                217,
                600,
                -0.052009861916303635
            ]
        ],
        "Landmark9": [
            [
                216,
                562,
                -0.06391093879938126
            ]
        ],
        "Landmark10": [
            [
                166,
                716,
                -0.020537136122584343
            ]
        ],
        "Landmark11": [
            [
                172,
                633,
                -0.051125165075063705
            ]
        ],
        "Landmark12": [
            [
                180,
                587,
                -0.07030265033245087
            ]
        ],
        "Landmark13": [
            [
                183,
                547,
                -0.08140359073877335
            ]
        ],
        "Landmark14": [
            [
                126,
                737,
                -0.03428005799651146
            ]
        ],
        "Landmark15": [
            [
                122,
                673,
                -0.08964768797159195
            ]
        ],
        "Landmark16": [
            [
                151,
                720,
                -0.10023395717144012
            ]
        ],
        "Landmark17": [
            [
                169,
                761,
                -0.09279286861419678
            ]
        ],
        "Landmark18": [
            [
                87,
                771,
                -0.050234127789735794
            ]
        ],
        "Landmark19": [
            [
                100,
                731,
                -0.09822972863912582
            ]
        ],
        "Landmark20": [
            [
                127,
                763,
                -0.10200843214988708
            ]
        ],
        "Landmark21": [
            [
                141,
                797,
                -0.09548088163137436
            ]
        ]
    },
    "frame2": {
        "Landmark1": [
            [
                156,
                910,
                6.661008455921547e-07
            ]
        ],
        "Landmark2": [
            [
                217,
                869,
                -0.03295927494764328
            ]
        ],
        "Landmark3": [
            [
                245,
                796,
                -0.04423048347234726
            ]
        ],
        "Landmark4": [
            [
                209,
                746,
                -0.05760457366704941
            ]
        ],
        "Landmark5": [
            [
                160,
                726,
                -0.06943124532699585
            ]
        ],
        "Landmark6": [
            [
                216,
                715,
                -0.011709417216479778
            ]
        ],
        "Landmark7": [
            [
                223,
                641,
                -0.0355377122759819
            ]
        ],
        "Landmark8": [
            [
                223,
                598,
                -0.051396310329437256
            ]
        ],
        "Landmark9": [
            [
                220,
                560,
                -0.06303016096353531
            ]
        ],
        "Landmark10": [
            [
                171,
                716,
                -0.02066713385283947
            ]
        ],
        "Landmark11": [
            [
                177,
                633,
                -0.050986699759960175
            ]
        ],
        "Landmark12": [
            [
                185,
                585,
                -0.06952326744794846
            ]
        ],
        "Landmark13": [
            [
                186,
                545,
                -0.0797443836927414
            ]
        ],
        "Landmark14": [
            [
                131,
                737,
                -0.035076770931482315
            ]
        ],
        "Landmark15": [
            [
                124,
                674,
                -0.0909125879406929
            ]
        ],
        "Landmark16": [
            [
                154,
                721,
                -0.10001464933156967
            ]
        ],
        "Landmark17": [
            [
                172,
                762,
                -0.09069586545228958
            ]
        ],
        "Landmark18": [
            [
                92,
                772,
                -0.051485951989889145
            ]
        ],
        "Landmark19": [
            [
                104,
                732,
                -0.09972874075174332
            ]
        ],
        "Landmark20": [
            [
                131,
                763,
                -0.10195718705654144
            ]
        ],
        "Landmark21": [
            [
                146,
                796,
                -0.093600794672966
            ]
        ]
    },
    "frame3": {
        "Landmark1": [
            [
                159,
                908,
                6.919145789652248e-07
            ]
        ],
        "Landmark2": [
            [
                220,
                868,
                -0.034215644001960754
            ]
        ],
        "Landmark3": [
            [
                248,
                797,
                -0.04558812826871872
            ]
        ],
        "Landmark4": [
            [
                213,
                747,
                -0.05875822529196739
            ]
        ],
        "Landmark5": [
            [
                164,
                726,
                -0.07017043232917786
            ]
        ],
        "Landmark6": [
            [
                218,
                715,
                -0.01271788589656353
            ]
        ],
        "Landmark7": [
            [
                226,
                641,
                -0.035975974053144455
            ]
        ],
        "Landmark8": [
            [
                226,
                598,
                -0.05154423043131828
            ]
        ],
        "Landmark9": [
            [
                224,
                559,
                -0.06325926631689072
            ]
        ],
        "Landmark10": [
            [
                174,
                716,
                -0.02069496177136898
            ]
        ],
        "Landmark11": [
            [
                179,
                634,
                -0.050338152796030045
            ]
        ],
        "Landmark12": [
            [
                188,
                588,
                -0.06868910789489746
            ]
        ],
        "Landmark13": [
            [
                190,
                547,
                -0.0791248306632042
            ]
        ],
        "Landmark14": [
            [
                134,
                736,
                -0.034064773470163345
            ]
        ],
        "Landmark15": [
            [
                129,
                674,
                -0.08986544609069824
            ]
        ],
        "Landmark16": [
            [
                158,
                721,
                -0.09815669059753418
            ]
        ],
        "Landmark17": [
            [
                174,
                763,
                -0.08833719044923782
            ]
        ],
        "Landmark18": [
            [
                96,
                771,
                -0.049627725034952164
            ]
        ],
        "Landmark19": [
            [
                108,
                732,
                -0.09891517460346222
            ]
        ],
        "Landmark20": [
            [
                136,
                763,
                -0.10200157016515732
            ]
        ],
        "Landmark21": [
            [
                150,
                795,
                -0.09402218461036682
            ]
        ]
    },
    "frame4": {
        "Landmark1": [
            [
                159,
                908,
                6.70404631364363e-07
            ]
        ],
        "Landmark2": [
            [
                221,
                870,
                -0.03450601547956467
            ]
        ],
        "Landmark3": [
            [
                248,
                797,
                -0.04590102657675743
            ]
        ],
        "Landmark4": [
            [
                213,
                746,
                -0.05890260636806488
            ]
        ],
        "Landmark5": [
            [
                164,
                725,
                -0.0700506642460823
            ]
        ],
        "Landmark6": [
            [
                220,
                717,
                -0.013461865484714508
            ]
        ],
        "Landmark7": [
            [
                228,
                643,
                -0.03710884600877762
            ]
        ],
        "Landmark8": [
            [
                229,
                601,
                -0.05274524539709091
            ]
        ],
        "Landmark9": [
            [
                227,
                562,
                -0.06451070308685303
            ]
        ],
        "Landmark10": [
            [
                176,
                717,
                -0.021351942792534828
            ]
        ],
        "Landmark11": [
            [
                182,
                635,
                -0.05175723880529404
            ]
        ],
        "Landmark12": [
            [
                191,
                587,
                -0.07028531283140182
            ]
        ],
        "Landmark13": [
            [
                193,
                547,
                -0.08081232756376266
            ]
        ],
        "Landmark14": [
            [
                136,
                737,
                -0.03470754623413086
            ]
        ],
        "Landmark15": [
            [
                131,
                673,
                -0.0908769816160202
            ]
        ],
        "Landmark16": [
            [
                160,
                720,
                -0.09949684143066406
            ]
        ],
        "Landmark17": [
            [
                176,
                761,
                -0.09014007449150085
            ]
        ],
        "Landmark18": [
            [
                97,
                770,
                -0.05027936398983002
            ]
        ],
        "Landmark19": [
            [
                111,
                732,
                -0.09984149038791656
            ]
        ],
        "Landmark20": [
            [
                138,
                763,
                -0.10326960682868958
            ]
        ],
        "Landmark21": [
            [
                151,
                796,
                -0.09583169221878052
            ]
        ]
    },
    "frame5": {
        "Landmark1": [
            [
                161,
                908,
                6.409794082173903e-07
            ]
        ],
        "Landmark2": [
            [
                222,
                866,
                -0.030970487743616104
            ]
        ],
        "Landmark3": [
            [
                250,
                795,
                -0.04199972748756409
            ]
        ],
        "Landmark4": [
            [
                215,
                745,
                -0.05546768009662628
            ]
        ],
        "Landmark5": [
            [
                167,
                726,
                -0.06751354038715363
            ]
        ],
        "Landmark6": [
            [
                221,
                716,
                -0.012927480041980743
            ]
        ],
        "Landmark7": [
            [
                227,
                643,
                -0.03689990192651749
            ]
        ],
        "Landmark8": [
            [
                227,
                600,
                -0.052377134561538696
            ]
        ],
        "Landmark9": [
            [
                224,
                562,
                -0.06381690502166748
            ]
        ],
        "Landmark10": [
            [
                176,
                715,
                -0.022819584235548973
            ]
        ],
        "Landmark11": [
            [
                182,
                632,
                -0.05316489562392235
            ]
        ],
        "Landmark12": [
            [
                192,
                585,
                -0.0702832043170929
            ]
        ],
        "Landmark13": [
            [
                196,
                546,
                -0.07960090786218643
            ]
        ],
        "Landmark14": [
            [
                136,
                735,
                -0.037712737917900085
            ]
        ],
        "Landmark15": [
            [
                131,
                669,
                -0.09312104433774948
            ]
        ],
        "Landmark16": [
            [
                160,
                718,
                -0.09952913224697113
            ]
        ],
        "Landmark17": [
            [
                175,
                762,
                -0.08843463659286499
            ]
        ],
        "Landmark18": [
            [
                98,
                769,
                -0.05453528091311455
            ]
        ],
        "Landmark19": [
            [
                111,
                729,
                -0.10187577456235886
            ]
        ],
        "Landmark20": [
            [
                139,
                760,
                -0.10278961807489395
            ]
        ],
        "Landmark21": [
            [
                153,
                793,
                -0.09365299344062805
            ]
        ]
    },
    "frame6": {
        "Landmark1": [
            [
                162,
                907,
                6.594331125597819e-07
            ]
        ],
        "Landmark2": [
            [
                223,
                868,
                -0.03386415168642998
            ]
        ],
        "Landmark3": [
            [
                251,
                795,
                -0.046006940305233
            ]
        ],
        "Landmark4": [
            [
                215,
                745,
                -0.05994493514299393
            ]
        ],
        "Landmark5": [
            [
                166,
                725,
                -0.07211204618215561
            ]
        ],
        "Landmark6": [
            [
                222,
                713,
                -0.016222717240452766
            ]
        ],
        "Landmark7": [
            [
                228,
                640,
                -0.041555870324373245
            ]
        ],
        "Landmark8": [
            [
                227,
                598,
                -0.05799136310815811
            ]
        ],
        "Landmark9": [
            [
                223,
                560,
                -0.0701051577925682
            ]
        ],
        "Landmark10": [
            [
                177,
                713,
                -0.025095265358686447
            ]
        ],
        "Landmark11": [
            [
                184,
                629,
                -0.05696338787674904
            ]
        ],
        "Landmark12": [
            [
                194,
                581,
                -0.07492183148860931
            ]
        ],
        "Landmark13": [
            [
                195,
                540,
                -0.08479075878858566
            ]
        ],
        "Landmark14": [
            [
                136,
                733,
                -0.03927776217460632
            ]
        ],
        "Landmark15": [
            [
                131,
                667,
                -0.09571555256843567
            ]
        ],
        "Landmark16": [
            [
                160,
                715,
                -0.1034768745303154
            ]
        ],
        "Landmark17": [
            [
                177,
                758,
                -0.09350736439228058
            ]
        ],
        "Landmark18": [
            [
                98,
                767,
                -0.055718354880809784
            ]
        ],
        "Landmark19": [
            [
                113,
                729,
                -0.10468630492687225
            ]
        ],
        "Landmark20": [
            [
                141,
                761,
                -0.10737373679876328
            ]
        ],
        "Landmark21": [
            [
                156,
                794,
                -0.09957270324230194
            ]
        ]
    },
    "frame7": {
        "Landmark1": [
            [
                161,
                907,
                6.623035346819961e-07
            ]
        ],
        "Landmark2": [
            [
                222,
                867,
                -0.03410525619983673
            ]
        ],
        "Landmark3": [
            [
                250,
                795,
                -0.04614729434251785
            ]
        ],
        "Landmark4": [
            [
                215,
                745,
                -0.060238517820835114
            ]
        ],
        "Landmark5": [
            [
                167,
                725,
                -0.0726514607667923
            ]
        ],
        "Landmark6": [
            [
                223,
                714,
                -0.015129530802369118
            ]
        ],
        "Landmark7": [
            [
                230,
                640,
                -0.0399903729557991
            ]
        ],
        "Landmark8": [
            [
                230,
                598,
                -0.056493330746889114
            ]
        ],
        "Landmark9": [
            [
                228,
                558,
                -0.06873442232608795
            ]
        ],
        "Landmark10": [
            [
                179,
                714,
                -0.023919327184557915
            ]
        ],
        "Landmark11": [
            [
                186,
                631,
                -0.05514105036854744
            ]
        ],
        "Landmark12": [
            [
                195,
                584,
                -0.07397811114788055
            ]
        ],
        "Landmark13": [
            [
                198,
                543,
                -0.08491993695497513
            ]
        ],
        "Landmark14": [
            [
                138,
                734,
                -0.038090918213129044
            ]
        ],
        "Landmark15": [
            [
                134,
                670,
                -0.09471752494573593
            ]
        ],
        "Landmark16": [
            [
                162,
                719,
                -0.10319211333990097
            ]
        ],
        "Landmark17": [
            [
                177,
                761,
                -0.0937575176358223
            ]
        ],
        "Landmark18": [
            [
                99,
                768,
                -0.05452921986579895
            ]
        ],
        "Landmark19": [
            [
                113,
                730,
                -0.10371702164411545
            ]
        ],
        "Landmark20": [
            [
                140,
                761,
                -0.10661067068576813
            ]
        ],
        "Landmark21": [
            [
                154,
                794,
                -0.09899891167879105
            ]
        ]
    },
    "frame8": {
        "Landmark1": [
            [
                161,
                906,
                6.537406989082228e-07
            ]
        ],
        "Landmark2": [
            [
                222,
                867,
                -0.03223280608654022
            ]
        ],
        "Landmark3": [
            [
                252,
                794,
                -0.04290849342942238
            ]
        ],
        "Landmark4": [
            [
                216,
                744,
                -0.05577904358506203
            ]
        ],
        "Landmark5": [
            [
                166,
                728,
                -0.06730583310127258
            ]
        ],
        "Landmark6": [
            [
                224,
                713,
                -0.013196345418691635
            ]
        ],
        "Landmark7": [
            [
                231,
                639,
                -0.03673194348812103
            ]
        ],
        "Landmark8": [
            [
                232,
                597,
                -0.05216781049966812
            ]
        ],
        "Landmark9": [
            [
                231,
                559,
                -0.06341423839330673
            ]
        ],
        "Landmark10": [
            [
                179,
                713,
                -0.022364046424627304
            ]
        ],
        "Landmark11": [
            [
                187,
                630,
                -0.05216033384203911
            ]
        ],
        "Landmark12": [
            [
                196,
                582,
                -0.06967046111822128
            ]
        ],
        "Landmark13": [
            [
                198,
                541,
                -0.07925377786159515
            ]
        ],
        "Landmark14": [
            [
                138,
                733,
                -0.03673335164785385
            ]
        ],
        "Landmark15": [
            [
                134,
                669,
                -0.09199997037649155
            ]
        ],
        "Landmark16": [
            [
                161,
                717,
                -0.09993525594472885
            ]
        ],
        "Landmark17": [
            [
                176,
                760,
                -0.08983143419027328
            ]
        ],
        "Landmark18": [
            [
                99,
                767,
                -0.0531202033162117
            ]
        ],
        "Landmark19": [
            [
                113,
                727,
                -0.10066267848014832
            ]
        ],
        "Landmark20": [
            [
                140,
                760,
                -0.10199170559644699
            ]
        ],
        "Landmark21": [
            [
                153,
                793,
                -0.0930950865149498
            ]
        ]
    },
    "frame9": {
        "Landmark1": [
            [
                158,
                907,
                6.870458264529589e-07
            ]
        ],
        "Landmark2": [
            [
                220,
                868,
                -0.03192008286714554
            ]
        ],
        "Landmark3": [
            [
                250,
                795,
                -0.04277357831597328
            ]
        ],
        "Landmark4": [
            [
                215,
                745,
                -0.055981963872909546
            ]
        ],
        "Landmark5": [
            [
                165,
                731,
                -0.06815415620803833
            ]
        ],
        "Landmark6": [
            [
                222,
                716,
                -0.014865842647850513
            ]
        ],
        "Landmark7": [
            [
                231,
                642,
                -0.03884798288345337
            ]
        ],
        "Landmark8": [
            [
                234,
                601,
                -0.05417345091700554
            ]
        ],
        "Landmark9": [
            [
                234,
                563,
                -0.06529046595096588
            ]
        ],
        "Landmark10": [
            [
                177,
                716,
                -0.024498092010617256
            ]
        ],
        "Landmark11": [
            [
                187,
                632,
                -0.05449032783508301
            ]
        ],
        "Landmark12": [
            [
                197,
                585,
                -0.07144352048635483
            ]
        ],
        "Landmark13": [
            [
                202,
                544,
                -0.0805349200963974
            ]
        ],
        "Landmark14": [
            [
                137,
                736,
                -0.03905190899968147
            ]
        ],
        "Landmark15": [
            [
                134,
                673,
                -0.09543575346469879
            ]
        ],
        "Landmark16": [
            [
                160,
                724,
                -0.10225211083889008
            ]
        ],
        "Landmark17": [
            [
                173,
                767,
                -0.09069658815860748
            ]
        ],
        "Landmark18": [
            [
                97,
                770,
                -0.055482082068920135
            ]
        ],
        "Landmark19": [
            [
                111,
                731,
                -0.10333345085382462
            ]
        ],
        "Landmark20": [
            [
                138,
                764,
                -0.10366015136241913
            ]
        ],
        "Landmark21": [
            [
                151,
                797,
                -0.09373511373996735
            ]
        ]
    },
    "frame10": {
        "Landmark1": [
            [
                154,
                911,
                7.001322614996752e-07
            ]
        ],
        "Landmark2": [
            [
                218,
                867,
                -0.029339205473661423
            ]
        ],
        "Landmark3": [
            [
                248,
                795,
                -0.03886250779032707
            ]
        ],
        "Landmark4": [
            [
                214,
                746,
                -0.050610803067684174
            ]
        ],
        "Landmark5": [
            [
                165,
                747,
                -0.062103208154439926
            ]
        ],
        "Landmark6": [
            [
                219,
                728,
                -0.0163149181753397
            ]
        ],
        "Landmark7": [
            [
                232,
                661,
                -0.03791791573166847
            ]
        ],
        "Landmark8": [
            [
                238,
                623,
                -0.05290522798895836
            ]
        ],
        "Landmark9": [
            [
                242,
                586,
                -0.0647607296705246
            ]
        ],
        "Landmark10": [
            [
                175,
                725,
                -0.025395551696419716
            ]
        ],
        "Landmark11": [
            [
                191,
                650,
                -0.05181334540247917
            ]
        ],
        "Landmark12": [
            [
                203,
                604,
                -0.06726305931806564
            ]
        ],
        "Landmark13": [
            [
                211,
                563,
                -0.07691477239131927
            ]
        ],
        "Landmark14": [
            [
                133,
                741,
                -0.03850071504712105
            ]
        ],
        "Landmark15": [
            [
                133,
                678,
                -0.08811789751052856
            ]
        ],
        "Landmark16": [
            [
                150,
                726,
                -0.09460409730672836
            ]
        ],
        "Landmark17": [
            [
                160,
                770,
                -0.08536271750926971
            ]
        ],
        "Landmark18": [
            [
                92,
                771,
                -0.05364221706986427
            ]
        ],
        "Landmark19": [
            [
                108,
                737,
                -0.09707099199295044
            ]
        ],
        "Landmark20": [
            [
                132,
                771,
                -0.09789018332958221
            ]
        ],
        "Landmark21": [
            [
                145,
                807,
                -0.08966318517923355
            ]
        ]
    },
    "frame11": {
        "Landmark1": [
            [
                163,
                916,
                -1.2448884945115424e-07
            ]
        ],
        "Landmark2": [
            [
                221,
                874,
                -0.023188969120383263
            ]
        ],
        "Landmark3": [
            [
                250,
                807,
                -0.03958539664745331
            ]
        ],
        "Landmark4": [
            [
                218,
                768,
                -0.05937937647104263
            ]
        ],
        "Landmark5": [
            [
                174,
                754,
                -0.07664760202169418
            ]
        ],
        "Landmark6": [
            [
                215,
                740,
                -0.015110225416719913
            ]
        ],
        "Landmark7": [
            [
                219,
                688,
                -0.06145195662975311
            ]
        ],
        "Landmark8": [
            [
                231,
                717,
                -0.09333129972219467
            ]
        ],
        "Landmark9": [
            [
                234,
                751,
                -0.10903021693229675
            ]
        ],
        "Landmark10": [
            [
                169,
                744,
                -0.026270655915141106
            ]
        ],
        "Landmark11": [
            [
                177,
                696,
                -0.07759594172239304
            ]
        ],
        "Landmark12": [
            [
                190,
                747,
                -0.09832822531461716
            ]
        ],
        "Landmark13": [
            [
                189,
                784,
                -0.10211574286222458
            ]
        ],
        "Landmark14": [
            [
                124,
                759,
                -0.04326685145497322
            ]
        ],
        "Landmark15": [
            [
                124,
                704,
                -0.09514465928077698
            ]
        ],
        "Landmark16": [
            [
                144,
                764,
                -0.09290675073862076
            ]
        ],
        "Landmark17": [
            [
                151,
                805,
                -0.0795927420258522
            ]
        ],
        "Landmark18": [
            [
                80,
                784,
                -0.06230698898434639
            ]
        ],
        "Landmark19": [
            [
                91,
                763,
                -0.10361628979444504
            ]
        ],
        "Landmark20": [
            [
                117,
                807,
                -0.10021037608385086
            ]
        ],
        "Landmark21": [
            [
                131,
                834,
                -0.08880016952753067
            ]
        ]
    },
    "frame12": {
        "Landmark1": [
            [
                155,
                923,
                -3.2767272273304116e-07
            ]
        ],
        "Landmark2": [
            [
                217,
                886,
                -0.03871055692434311
            ]
        ],
        "Landmark3": [
            [
                256,
                836,
                -0.06831587851047516
            ]
        ],
        "Landmark4": [
            [
                247,
                805,
                -0.09962285310029984
            ]
        ],
        "Landmark5": [
            [
                206,
                797,
                -0.12693412601947784
            ]
        ],
        "Landmark6": [
            [
                211,
                733,
                -0.03518455848097801
            ]
        ],
        "Landmark7": [
            [
                218,
                718,
                -0.09994962811470032
            ]
        ],
        "Landmark8": [
            [
                223,
                772,
                -0.14325247704982758
            ]
        ],
        "Landmark9": [
            [
                227,
                817,
                -0.16357702016830444
            ]
        ],
        "Landmark10": [
            [
                158,
                738,
                -0.04442691057920456
            ]
        ],
        "Landmark11": [
            [
                168,
                722,
                -0.11368362605571747
            ]
        ],
        "Landmark12": [
            [
                180,
                787,
                -0.1381196677684784
            ]
        ],
        "Landmark13": [
            [
                188,
                836,
                -0.139358788728714
            ]
        ],
        "Landmark14": [
            [
                108,
                757,
                -0.061519887298345566
            ]
        ],
        "Landmark15": [
            [
                113,
                745,
                -0.12462406605482101
            ]
        ],
        "Landmark16": [
            [
                136,
                808,
                -0.12564004957675934
            ]
        ],
        "Landmark17": [
            [
                152,
                850,
                -0.1102396622300148
            ]
        ],
        "Landmark18": [
            [
                67,
                788,
                -0.08240589499473572
            ]
        ],
        "Landmark19": [
            [
                78,
                795,
                -0.12356289476156235
            ]
        ],
        "Landmark20": [
            [
                106,
                838,
                -0.12043166905641556
            ]
        ],
        "Landmark21": [
            [
                127,
                863,
                -0.10753770172595978
            ]
        ]
    },
    "frame13": {
        "Landmark1": [
            [
                151,
                936,
                -5.390655815062928e-07
            ]
        ],
        "Landmark2": [
            [
                213,
                904,
                -0.05067376419901848
            ]
        ],
        "Landmark3": [
            [
                255,
                866,
                -0.0863829180598259
            ]
        ],
        "Landmark4": [
            [
                264,
                839,
                -0.11915712058544159
            ]
        ],
        "Landmark5": [
            [
                244,
                820,
                -0.14695651829242706
            ]
        ],
        "Landmark6": [
            [
                217,
                726,
                -0.0514490008354187
            ]
        ],
        "Landmark7": [
            [
                213,
                765,
                -0.11544758826494217
            ]
        ],
        "Landmark8": [
            [
                213,
                828,
                -0.1602661907672882
            ]
        ],
        "Landmark9": [
            [
                211,
                873,
                -0.18186825513839722
            ]
        ],
        "Landmark10": [
            [
                159,
                726,
                -0.052982766181230545
            ]
        ],
        "Landmark11": [
            [
                155,
                772,
                -0.11867274343967438
            ]
        ],
        "Landmark12": [
            [
                165,
                841,
                -0.1457255333662033
            ]
        ],
        "Landmark13": [
            [
                174,
                889,
                -0.15089893341064453
            ]
        ],
        "Landmark14": [
            [
                105,
                748,
                -0.06160251796245575
            ]
        ],
        "Landmark15": [
            [
                103,
                789,
                -0.12021739780902863
            ]
        ],
        "Landmark16": [
            [
                124,
                846,
                -0.12707723677158356
            ]
        ],
        "Landmark17": [
            [
                142,
                882,
                -0.11753635853528976
            ]
        ],
        "Landmark18": [
            [
                64,
                783,
                -0.07516088336706161
            ]
        ],
        "Landmark19": [
            [
                67,
                821,
                -0.11510095745325089
            ]
        ],
        "Landmark20": [
            [
                93,
                864,
                -0.11677240580320358
            ]
        ],
        "Landmark21": [
            [
                117,
                886,
                -0.10665208101272583
            ]
        ]
    },
    "frame14": {
        "Landmark1": [
            [
                143,
                938,
                -5.350668743631104e-07
            ]
        ],
        "Landmark2": [
            [
                208,
                908,
                -0.05295085161924362
            ]
        ],
        "Landmark3": [
            [
                258,
                872,
                -0.09054267406463623
            ]
        ],
        "Landmark4": [
            [
                266,
                853,
                -0.1236514151096344
            ]
        ],
        "Landmark5": [
            [
                237,
                849,
                -0.15376785397529602
            ]
        ],
        "Landmark6": [
            [
                219,
                739,
                -0.060174811631441116
            ]
        ],
        "Landmark7": [
            [
                216,
                800,
                -0.12402383983135223
            ]
        ],
        "Landmark8": [
            [
                214,
                865,
                -0.16992433369159698
            ]
        ],
        "Landmark9": [
            [
                208,
                911,
                -0.19230225682258606
            ]
        ],
        "Landmark10": [
            [
                158,
                738,
                -0.05906162038445473
            ]
        ],
        "Landmark11": [
            [
                156,
                799,
                -0.12357620894908905
            ]
        ],
        "Landmark12": [
            [
                164,
                874,
                -0.1507653295993805
            ]
        ],
        "Landmark13": [
            [
                170,
                927,
                -0.15694789588451385
            ]
        ],
        "Landmark14": [
            [
                104,
                758,
                -0.06393039971590042
            ]
        ],
        "Landmark15": [
            [
                101,
                811,
                -0.12196261435747147
            ]
        ],
        "Landmark16": [
            [
                123,
                872,
                -0.13059085607528687
            ]
        ],
        "Landmark17": [
            [
                141,
                914,
                -0.1220678985118866
            ]
        ],
        "Landmark18": [
            [
                61,
                792,
                -0.0733969435095787
            ]
        ],
        "Landmark19": [
            [
                62,
                829,
                -0.11146098375320435
            ]
        ],
        "Landmark20": [
            [
                88,
                874,
                -0.1122015044093132
            ]
        ],
        "Landmark21": [
            [
                112,
                900,
                -0.10205139219760895
            ]
        ]
    },
    "frame15": {
        "Landmark1": [
            [
                142,
                953,
                -6.600976121262647e-07
            ]
        ],
        "Landmark2": [
            [
                206,
                926,
                -0.045815035700798035
            ]
        ],
        "Landmark3": [
            [
                252,
                891,
                -0.0800643116235733
            ]
        ],
        "Landmark4": [
            [
                267,
                869,
                -0.11208023130893707
            ]
        ],
        "Landmark5": [
            [
                245,
                853,
                -0.14063327014446259
            ]
        ],
        "Landmark6": [
            [
                224,
                748,
                -0.04743187874555588
            ]
        ],
        "Landmark7": [
            [
                225,
                805,
                -0.10836498439311981
            ]
        ],
        "Landmark8": [
            [
                220,
                867,
                -0.15359118580818176
            ]
        ],
        "Landmark9": [
            [
                211,
                911,
                -0.1758606731891632
            ]
        ],
        "Landmark10": [
            [
                167,
                745,
                -0.04887177795171738
            ]
        ],
        "Landmark11": [
            [
                169,
                809,
                -0.1108454018831253
            ]
        ],
        "Landmark12": [
            [
                173,
                884,
                -0.13883768022060394
            ]
        ],
        "Landmark13": [
            [
                175,
                937,
                -0.14582227170467377
            ]
        ],
        "Landmark14": [
            [
                113,
                763,
                -0.05604596436023712
            ]
        ],
        "Landmark15": [
            [
                115,
                816,
                -0.11444974690675735
            ]
        ],
        "Landmark16": [
            [
                135,
                880,
                -0.12316161394119263
            ]
        ],
        "Landmark17": [
            [
                151,
                925,
                -0.11413740366697311
            ]
        ],
        "Landmark18": [
            [
                68,
                796,
                -0.06705448776483536
            ]
        ],
        "Landmark19": [
            [
                71,
                831,
                -0.10929591208696365
            ]
        ],
        "Landmark20": [
            [
                97,
                878,
                -0.11111254245042801
            ]
        ],
        "Landmark21": [
            [
                121,
                906,
                -0.10007825493812561
            ]
        ]
    },
    "frame16": {
        "Landmark1": [
            [
                142,
                948,
                -5.534901106329926e-07
            ]
        ],
        "Landmark2": [
            [
                204,
                923,
                -0.0533231720328331
            ]
        ],
        "Landmark3": [
            [
                250,
                892,
                -0.09165926277637482
            ]
        ],
        "Landmark4": [
            [
                269,
                871,
                -0.12565186619758606
            ]
        ],
        "Landmark5": [
            [
                248,
                854,
                -0.1561381071805954
            ]
        ],
        "Landmark6": [
            [
                218,
                750,
                -0.06178179383277893
            ]
        ],
        "Landmark7": [
            [
                221,
                812,
                -0.129896879196167
            ]
        ],
        "Landmark8": [
            [
                220,
                876,
                -0.1794493943452835
            ]
        ],
        "Landmark9": [
            [
                214,
                923,
                -0.20315217971801758
            ]
        ],
        "Landmark10": [
            [
                160,
                748,
                -0.05987943708896637
            ]
        ],
        "Landmark11": [
            [
                161,
                813,
                -0.1283842772245407
            ]
        ],
        "Landmark12": [
            [
                167,
                889,
                -0.1575421392917633
            ]
        ],
        "Landmark13": [
            [
                171,
                943,
                -0.16446775197982788
            ]
        ],
        "Landmark14": [
            [
                107,
                769,
                -0.06427125632762909
            ]
        ],
        "Landmark15": [
            [
                105,
                822,
                -0.12530139088630676
            ]
        ],
        "Landmark16": [
            [
                124,
                882,
                -0.13472101092338562
            ]
        ],
        "Landmark17": [
            [
                142,
                925,
                -0.12616515159606934
            ]
        ],
        "Landmark18": [
            [
                65,
                803,
                -0.07317690551280975
            ]
        ],
        "Landmark19": [
            [
                64,
                841,
                -0.11452195048332214
            ]
        ],
        "Landmark20": [
            [
                90,
                884,
                -0.11741496622562408
            ]
        ],
        "Landmark21": [
            [
                115,
                910,
                -0.10784664750099182
            ]
        ]
    },
    "frame17": {
        "Landmark1": [
            [
                142,
                942,
                -5.320112563822477e-07
            ]
        ],
        "Landmark2": [
            [
                202,
                917,
                -0.05181451141834259
            ]
        ],
        "Landmark3": [
            [
                248,
                888,
                -0.09011747688055038
            ]
        ],
        "Landmark4": [
            [
                269,
                870,
                -0.12462639063596725
            ]
        ],
        "Landmark5": [
            [
                248,
                857,
                -0.15573306381702423
            ]
        ],
        "Landmark6": [
            [
                215,
                750,
                -0.0627574697136879
            ]
        ],
        "Landmark7": [
            [
                218,
                808,
                -0.13091880083084106
            ]
        ],
        "Landmark8": [
            [
                218,
                872,
                -0.17944560945034027
            ]
        ],
        "Landmark9": [
            [
                213,
                921,
                -0.2022191733121872
            ]
        ],
        "Landmark10": [
            [
                157,
                749,
                -0.061965297907590866
            ]
        ],
        "Landmark11": [
            [
                158,
                813,
                -0.1301904320716858
            ]
        ],
        "Landmark12": [
            [
                166,
                888,
                -0.15836086869239807
            ]
        ],
        "Landmark13": [
            [
                171,
                942,
                -0.16464459896087646
            ]
        ],
        "Landmark14": [
            [
                103,
                770,
                -0.06730900704860687
            ]
        ],
        "Landmark15": [
            [
                103,
                821,
                -0.1284611076116562
            ]
        ],
        "Landmark16": [
            [
                123,
                880,
                -0.13707269728183746
            ]
        ],
        "Landmark17": [
            [
                140,
                922,
                -0.12797535955905914
            ]
        ],
        "Landmark18": [
            [
                62,
                804,
                -0.07706855237483978
            ]
        ],
        "Landmark19": [
            [
                64,
                842,
                -0.11927814781665802
            ]
        ],
        "Landmark20": [
            [
                91,
                885,
                -0.12178044021129608
            ]
        ],
        "Landmark21": [
            [
                117,
                911,
                -0.11177083849906921
            ]
        ]
    },
    "frame18": {
        "Landmark1": [
            [
                143,
                946,
                -4.920740366287646e-07
            ]
        ],
        "Landmark2": [
            [
                204,
                919,
                -0.05401160195469856
            ]
        ],
        "Landmark3": [
            [
                250,
                887,
                -0.09280022233724594
            ]
        ],
        "Landmark4": [
            [
                268,
                868,
                -0.127503901720047
            ]
        ],
        "Landmark5": [
            [
                246,
                856,
                -0.15844625234603882
            ]
        ],
        "Landmark6": [
            [
                215,
                748,
                -0.06293733417987823
            ]
        ],
        "Landmark7": [
            [
                219,
                806,
                -0.13103532791137695
            ]
        ],
        "Landmark8": [
            [
                219,
                871,
                -0.17928741872310638
            ]
        ],
        "Landmark9": [
            [
                213,
                919,
                -0.2021096795797348
            ]
        ],
        "Landmark10": [
            [
                157,
                748,
                -0.06126108765602112
            ]
        ],
        "Landmark11": [
            [
                159,
                813,
                -0.13088905811309814
            ]
        ],
        "Landmark12": [
            [
                167,
                888,
                -0.15989980101585388
            ]
        ],
        "Landmark13": [
            [
                173,
                940,
                -0.1665324866771698
            ]
        ],
        "Landmark14": [
            [
                104,
                770,
                -0.06601472944021225
            ]
        ],
        "Landmark15": [
            [
                105,
                823,
                -0.12866707146167755
            ]
        ],
        "Landmark16": [
            [
                127,
                883,
                -0.1387588083744049
            ]
        ],
        "Landmark17": [
            [
                146,
                924,
                -0.13017995655536652
            ]
        ],
        "Landmark18": [
            [
                62,
                804,
                -0.07529492676258087
            ]
        ],
        "Landmark19": [
            [
                66,
                841,
                -0.11800403892993927
            ]
        ],
        "Landmark20": [
            [
                93,
                885,
                -0.12170254439115524
            ]
        ],
        "Landmark21": [
            [
                119,
                910,
                -0.1124945804476738
            ]
        ]
    },
    "frame19": {
        "Landmark1": [
            [
                144,
                947,
                -4.919427283311961e-07
            ]
        ],
        "Landmark2": [
            [
                205,
                921,
                -0.0566805824637413
            ]
        ],
        "Landmark3": [
            [
                250,
                888,
                -0.09649910032749176
            ]
        ],
        "Landmark4": [
            [
                268,
                868,
                -0.13167795538902283
            ]
        ],
        "Landmark5": [
            [
                247,
                853,
                -0.16271841526031494
            ]
        ],
        "Landmark6": [
            [
                217,
                748,
                -0.06405315548181534
            ]
        ],
        "Landmark7": [
            [
                220,
                804,
                -0.13391248881816864
            ]
        ],
        "Landmark8": [
            [
                219,
                869,
                -0.1832445114850998
            ]
        ],
        "Landmark9": [
            [
                214,
                917,
                -0.20653903484344482
            ]
        ],
        "Landmark10": [
            [
                158,
                747,
                -0.06158486753702164
            ]
        ],
        "Landmark11": [
            [
                160,
                809,
                -0.13361744582653046
            ]
        ],
        "Landmark12": [
            [
                168,
                886,
                -0.16369546949863434
            ]
        ],
        "Landmark13": [
            [
                173,
                939,
                -0.17034149169921875
            ]
        ],
        "Landmark14": [
            [
                105,
                769,
                -0.06591662764549255
            ]
        ],
        "Landmark15": [
            [
                106,
                818,
                -0.13178744912147522
            ]
        ],
        "Landmark16": [
            [
                128,
                880,
                -0.1421792358160019
            ]
        ],
        "Landmark17": [
            [
                146,
                922,
                -0.1329813301563263
            ]
        ],
        "Landmark18": [
            [
                63,
                804,
                -0.07478480786085129
            ]
        ],
        "Landmark19": [
            [
                67,
                840,
                -0.12034730613231659
            ]
        ],
        "Landmark20": [
            [
                95,
                884,
                -0.12453555315732956
            ]
        ],
        "Landmark21": [
            [
                121,
                909,
                -0.11508650332689285
            ]
        ]
    },
    "frame20": {
        "Landmark1": [
            [
                146,
                943,
                -5.103901230540941e-07
            ]
        ],
        "Landmark2": [
            [
                209,
                915,
                -0.05144413933157921
            ]
        ],
        "Landmark3": [
            [
                254,
                882,
                -0.0890127569437027
            ]
        ],
        "Landmark4": [
            [
                268,
                864,
                -0.12288012355566025
            ]
        ],
        "Landmark5": [
            [
                243,
                856,
                -0.15367092192173004
            ]
        ],
        "Landmark6": [
            [
                217,
                747,
                -0.05952172726392746
            ]
        ],
        "Landmark7": [
            [
                220,
                810,
                -0.12536853551864624
            ]
        ],
        "Landmark8": [
            [
                219,
                874,
                -0.17262603342533112
            ]
        ],
        "Landmark9": [
            [
                213,
                921,
                -0.19537201523780823
            ]
        ],
        "Landmark10": [
            [
                157,
                747,
                -0.05953973904252052
            ]
        ],
        "Landmark11": [
            [
                159,
                809,
                -0.1265426129102707
            ]
        ],
        "Landmark12": [
            [
                167,
                885,
                -0.1549368053674698
            ]
        ],
        "Landmark13": [
            [
                172,
                939,
                -0.1618117392063141
            ]
        ],
        "Landmark14": [
            [
                103,
                769,
                -0.06553388386964798
            ]
        ],
        "Landmark15": [
            [
                104,
                819,
                -0.12713341414928436
            ]
        ],
        "Landmark16": [
            [
                125,
                881,
                -0.1363077312707901
            ]
        ],
        "Landmark17": [
            [
                142,
                923,
                -0.12741252779960632
            ]
        ],
        "Landmark18": [
            [
                60,
                804,
                -0.07568241655826569
            ]
        ],
        "Landmark19": [
            [
                63,
                838,
                -0.11739824712276459
            ]
        ],
        "Landmark20": [
            [
                89,
                882,
                -0.11904333531856537
            ]
        ],
        "Landmark21": [
            [
                113,
                908,
                -0.10882052779197693
            ]
        ]
    },
    "frame21": {
        "Landmark1": [
            [
                139,
                948,
                -6.383043000823818e-07
            ]
        ],
        "Landmark2": [
            [
                202,
                922,
                -0.05117059499025345
            ]
        ],
        "Landmark3": [
            [
                250,
                890,
                -0.0880374163389206
            ]
        ],
        "Landmark4": [
            [
                268,
                868,
                -0.12170954048633575
            ]
        ],
        "Landmark5": [
            [
                245,
                855,
                -0.1520991027355194
            ]
        ],
        "Landmark6": [
            [
                219,
                748,
                -0.05345463007688522
            ]
        ],
        "Landmark7": [
            [
                223,
                807,
                -0.11668627709150314
            ]
        ],
        "Landmark8": [
            [
                219,
                870,
                -0.16332405805587769
            ]
        ],
        "Landmark9": [
            [
                210,
                915,
                -0.18602290749549866
            ]
        ],
        "Landmark10": [
            [
                162,
                746,
                -0.05252775549888611
            ]
        ],
        "Landmark11": [
            [
                166,
                809,
                -0.1166597232222557
            ]
        ],
        "Landmark12": [
            [
                172,
                885,
                -0.14503897726535797
            ]
        ],
        "Landmark13": [
            [
                175,
                938,
                -0.15193946659564972
            ]
        ],
        "Landmark14": [
            [
                109,
                765,
                -0.05779655650258064
            ]
        ],
        "Landmark15": [
            [
                112,
                820,
                -0.11677298694849014
            ]
        ],
        "Landmark16": [
            [
                132,
                884,
                -0.1254313439130783
            ]
        ],
        "Landmark17": [
            [
                148,
                928,
                -0.11614654958248138
            ]
        ],
        "Landmark18": [
            [
                65,
                798,
                -0.06750558316707611
            ]
        ],
        "Landmark19": [
            [
                68,
                832,
                -0.10804582387208939
            ]
        ],
        "Landmark20": [
            [
                93,
                877,
                -0.10978115350008011
            ]
        ],
        "Landmark21": [
            [
                115,
                904,
                -0.09918373823165894
            ]
        ]
    },
    "frame22": {
        "Landmark1": [
            [
                139,
                945,
                -5.20698563377664e-07
            ]
        ],
        "Landmark2": [
            [
                199,
                918,
                -0.05553341656923294
            ]
        ],
        "Landmark3": [
            [
                246,
                888,
                -0.09621390700340271
            ]
        ],
        "Landmark4": [
            [
                267,
                869,
                -0.1329755336046219
            ]
        ],
        "Landmark5": [
            [
                246,
                856,
                -0.16550034284591675
            ]
        ],
        "Landmark6": [
            [
                213,
                746,
                -0.06255272775888443
            ]
        ],
        "Landmark7": [
            [
                216,
                804,
                -0.13245026767253876
            ]
        ],
        "Landmark8": [
            [
                214,
                869,
                -0.18162712454795837
            ]
        ],
        "Landmark9": [
            [
                208,
                915,
                -0.20456919074058533
            ]
        ],
        "Landmark10": [
            [
                154,
                746,
                -0.06104820966720581
            ]
        ],
        "Landmark11": [
            [
                155,
                812,
                -0.13272207975387573
            ]
        ],
        "Landmark12": [
            [
                164,
                888,
                -0.1630484163761139
            ]
        ],
        "Landmark13": [
            [
                170,
                941,
                -0.16981291770935059
            ]
        ],
        "Landmark14": [
            [
                101,
                769,
                -0.06619545072317123
            ]
        ],
        "Landmark15": [
            [
                103,
                821,
                -0.13194483518600464
            ]
        ],
        "Landmark16": [
            [
                127,
                884,
                -0.14208871126174927
            ]
        ],
        "Landmark17": [
            [
                146,
                927,
                -0.13234008848667145
            ]
        ],
        "Landmark18": [
            [
                60,
                804,
                -0.07580751925706863
            ]
        ],
        "Landmark19": [
            [
                65,
                839,
                -0.12141362577676773
            ]
        ],
        "Landmark20": [
            [
                93,
                883,
                -0.12501288950443268
            ]
        ],
        "Landmark21": [
            [
                118,
                910,
                -0.11460665613412857
            ]
        ]
    },
    "frame23": {
        "Landmark1": [
            [
                141,
                949,
                -5.440283530333545e-07
            ]
        ],
        "Landmark2": [
            [
                204,
                923,
                -0.05346982553601265
            ]
        ],
        "Landmark3": [
            [
                251,
                889,
                -0.09098361432552338
            ]
        ],
        "Landmark4": [
            [
                265,
                867,
                -0.12458459287881851
            ]
        ],
        "Landmark5": [
            [
                241,
                855,
                -0.154560387134552
            ]
        ],
        "Landmark6": [
            [
                216,
                748,
                -0.05745035782456398
            ]
        ],
        "Landmark7": [
            [
                216,
                808,
                -0.1250600814819336
            ]
        ],
        "Landmark8": [
            [
                214,
                873,
                -0.17374733090400696
            ]
        ],
        "Landmark9": [
            [
                207,
                921,
                -0.19676196575164795
            ]
        ],
        "Landmark10": [
            [
                157,
                748,
                -0.056026261299848557
            ]
        ],
        "Landmark11": [
            [
                157,
                812,
                -0.1251470297574997
            ]
        ],
        "Landmark12": [
            [
                165,
                888,
                -0.15514689683914185
            ]
        ],
        "Landmark13": [
            [
                170,
                942,
                -0.16206452250480652
            ]
        ],
        "Landmark14": [
            [
                104,
                769,
                -0.06113644316792488
            ]
        ],
        "Landmark15": [
            [
                104,
                822,
                -0.12531155347824097
            ]
        ],
        "Landmark16": [
            [
                126,
                886,
                -0.13562160730361938
            ]
        ],
        "Landmark17": [
            [
                144,
                930,
                -0.12626342475414276
            ]
        ],
        "Landmark18": [
            [
                60,
                803,
                -0.07053136080503464
            ]
        ],
        "Landmark19": [
            [
                63,
                838,
                -0.11477073282003403
            ]
        ],
        "Landmark20": [
            [
                90,
                883,
                -0.11790731549263
            ]
        ],
        "Landmark21": [
            [
                115,
                908,
                -0.10759700834751129
            ]
        ]
    },
    "frame24": {
        "Landmark1": [
            [
                139,
                948,
                -5.672353609043057e-07
            ]
        ],
        "Landmark2": [
            [
                198,
                924,
                -0.0539320632815361
            ]
        ],
        "Landmark3": [
            [
                244,
                892,
                -0.092875637114048
            ]
        ],
        "Landmark4": [
            [
                265,
                872,
                -0.12782855331897736
            ]
        ],
        "Landmark5": [
            [
                246,
                855,
                -0.15859010815620422
            ]
        ],
        "Landmark6": [
            [
                213,
                748,
                -0.05976279824972153
            ]
        ],
        "Landmark7": [
            [
                217,
                807,
                -0.12771014869213104
            ]
        ],
        "Landmark8": [
            [
                215,
                871,
                -0.17579945921897888
            ]
        ],
        "Landmark9": [
            [
                209,
                918,
                -0.19809943437576294
            ]
        ],
        "Landmark10": [
            [
                156,
                747,
                -0.05821921303868294
            ]
        ],
        "Landmark11": [
            [
                158,
                812,
                -0.12762565910816193
            ]
        ],
        "Landmark12": [
            [
                166,
                888,
                -0.15730176866054535
            ]
        ],
        "Landmark13": [
            [
                172,
                941,
                -0.16379235684871674
            ]
        ],
        "Landmark14": [
            [
                103,
                769,
                -0.06306142359972
            ]
        ],
        "Landmark15": [
            [
                105,
                821,
                -0.12652474641799927
            ]
        ],
        "Landmark16": [
            [
                127,
                884,
                -0.1359674334526062
            ]
        ],
        "Landmark17": [
            [
                146,
                928,
                -0.12622828781604767
            ]
        ],
        "Landmark18": [
            [
                60,
                803,
                -0.0722503662109375
            ]
        ],
        "Landmark19": [
            [
                63,
                839,
                -0.11670155823230743
            ]
        ],
        "Landmark20": [
            [
                90,
                883,
                -0.11973018944263458
            ]
        ],
        "Landmark21": [
            [
                114,
                910,
                -0.10896017402410507
            ]
        ]
    }
}